<?xml version = '1.0' encoding = 'UTF-8'?>
<FKIndexAssociation class="oracle.dbtools.crest.model.design.relational.FKIndexAssociation" directorySegmentName="seg_0" id="64AC9236-B064-878B-CE2E-53972002AF3C" name="BC_department_BC_employee_FK">
<createdBy>ashleyng</createdBy>
<createdTime>2014-04-12 18:20:31 UTC</createdTime>
<generatorID>7553F5F7-84F7-BC38-3469-EC8FAABB451F</generatorID>
<ownerDesignName>Business_contract_v2</ownerDesignName>
<containerWithKeyObject>E25B325F-2A77-F6DA-FFBB-52A248082168</containerWithKeyObject>
<deleteRule>NO ACTION</deleteRule>
<localFKIndex>AEFE55B8-73F4-93AE-6436-209C56FE4C9F</localFKIndex>
<keyObject>B1354D07-8DAC-54F5-8C73-50617BA831E6</keyObject>
<mandatory>false</mandatory>
<transferable>true</transferable>
<columnDependencyConstraintGenerateInDDL>true</columnDependencyConstraintGenerateInDDL>
</FKIndexAssociation>