<?xml version = '1.0' encoding = 'UTF-8'?>
<FKIndexAssociation class="oracle.dbtools.crest.model.design.relational.FKIndexAssociation" directorySegmentName="seg_0" id="16D5AEFA-FD66-7DC6-F9C3-C17803E9FC55" name="BC_document_BC_amendment_FK">
<createdBy>ashleyng</createdBy>
<createdTime>2014-04-06 19:32:36 UTC</createdTime>
<generatorID>BCF85238-6856-83E8-BA25-33195001D9AC</generatorID>
<ownerDesignName>Business_contract_v2</ownerDesignName>
<containerWithKeyObject>216C6309-F516-EAE9-100B-65FBABA03DF6</containerWithKeyObject>
<deleteRule>NO ACTION</deleteRule>
<localFKIndex>7132B20C-E6F8-D42E-DDDE-BE92C688ADB6</localFKIndex>
<keyObject>7F0023F8-EDDD-EEA6-0258-563EB57C1C55</keyObject>
<mandatory>false</mandatory>
<transferable>true</transferable>
<columnDependencyConstraintGenerateInDDL>true</columnDependencyConstraintGenerateInDDL>
</FKIndexAssociation>