<?xml version = '1.0' encoding = 'UTF-8'?>
<Diagram class="oracle.dbtools.crest.swingui.logical.DPVLogical" name="Logical" id="A7130678-4BF8-FBBB-8295-89E2CBBCFDBF">
<createdBy>Jared</createdBy>
<createdTime>2014-04-06 16:43:15 UTC</createdTime>
<autoRoute>false</autoRoute>
<boxInbox>true</boxInbox>
<showLegend>false</showLegend>
<showLabels>false</showLabels>
<showRelAttributes>false</showRelAttributes>
<showGrid>false</showGrid>
<diagramColor>-1</diagramColor>
<display>false</display>
<notation>2</notation>
<objectViews>
<OView class="oracle.dbtools.crest.swingui.logical.TVEntity" oid="12E352F4-40B1-14F6-E708-104FE9D9F304" otype="Entity" vid="9F644485-0BE1-F76D-036E-B1B4823BE5FE">
<hideElementsInCurrentOnly>false</hideElementsInCurrentOnly>
<bounds x="982" y="519" width="240" height="114"/>
</OView>
<OView class="oracle.dbtools.crest.swingui.logical.TVEntity" oid="2587B050-8FA8-04C8-57CD-0BAAC56E5D63" otype="Entity" vid="863BF41D-2138-0B14-92F0-C62DCE38712C">
<hideElementsInCurrentOnly>false</hideElementsInCurrentOnly>
<bounds x="458" y="4" width="231" height="130"/>
</OView>
<OView class="oracle.dbtools.crest.swingui.logical.TVEntity" oid="2FCE6FE3-585F-3846-ADCA-90CB59897BDA" otype="Entity" vid="7A1BDCD1-4C87-C46F-AA9D-636A775755B6">
<hideElementsInCurrentOnly>false</hideElementsInCurrentOnly>
<bounds x="10" y="299" width="221" height="102"/>
</OView>
<OView class="oracle.dbtools.crest.swingui.logical.TVEntity" oid="358A2A9A-D09D-E058-EDD4-2D4D3C2589EC" otype="Entity" vid="D836CA6E-3B79-7F6E-B62D-11BB7491EAA0">
<hideElementsInCurrentOnly>false</hideElementsInCurrentOnly>
<bounds x="137" y="0" width="204" height="113"/>
</OView>
<OView class="oracle.dbtools.crest.swingui.logical.TVEntity" oid="3A7020B2-1D13-3348-17F7-28BA7441AE59" otype="Entity" vid="95CCEA23-4139-0E69-4CB4-310AC9990181">
<hideElementsInCurrentOnly>false</hideElementsInCurrentOnly>
<bounds x="17" y="173" width="178" height="99"/>
</OView>
<OView class="oracle.dbtools.crest.swingui.logical.TVEntity" oid="44038AEA-A609-9FD5-E33E-C909F4182CA2" otype="Entity" vid="4F6CDB0B-B8B5-CA93-726A-9C340BDFDA1A">
<hideElementsInCurrentOnly>false</hideElementsInCurrentOnly>
<bounds x="664" y="398" width="257" height="172"/>
</OView>
<OView class="oracle.dbtools.crest.swingui.logical.TVEntity" oid="55F330FF-EF81-608B-B2AE-C1D7BA209BAF" otype="Entity" vid="668839F0-B981-A9AF-F122-644E4D57CA26">
<hideElementsInCurrentOnly>false</hideElementsInCurrentOnly>
<bounds x="675" y="162" width="220" height="144"/>
</OView>
<OView class="oracle.dbtools.crest.swingui.logical.TVEntity" oid="72A4E1BB-7E98-7E1D-55AB-DB7BFA694951" otype="Entity" vid="CA4BF46B-0E19-F79D-E360-842680E6AA9E">
<hideElementsInCurrentOnly>false</hideElementsInCurrentOnly>
<bounds x="669" y="672" width="217" height="228"/>
</OView>
<OView class="oracle.dbtools.crest.swingui.logical.TVEntity" oid="94BC28B4-1869-0709-1125-E7C4E5378A6A" otype="Entity" vid="D381CD95-20E2-6915-C7D4-B9BF6B244552">
<hideElementsInCurrentOnly>false</hideElementsInCurrentOnly>
<bounds x="8" y="418" width="252" height="144"/>
</OView>
<OView class="oracle.dbtools.crest.swingui.logical.TVEntity" oid="B3DE2677-361A-DF7E-5A56-BA1971AB8241" otype="Entity" vid="F7E93877-3995-E044-1E2A-DD487B960023">
<hideElementsInCurrentOnly>false</hideElementsInCurrentOnly>
<bounds x="954" y="167" width="222" height="130"/>
</OView>
<OView class="oracle.dbtools.crest.swingui.logical.TVEntity" oid="B78A39A6-90C9-2BF2-0DB7-01E27974EDCB" otype="Entity" vid="304506D0-FFBA-2498-3AD4-5DDDB6F5CD72">
<hideElementsInCurrentOnly>false</hideElementsInCurrentOnly>
<bounds x="303" y="694" width="195" height="144"/>
</OView>
<OView class="oracle.dbtools.crest.swingui.logical.TVEntity" oid="B8EB28B6-E728-51C4-6DFC-4F79F55F3B93" otype="Entity" vid="CC596B5D-87EF-9AD9-D44F-B559A1619A39">
<hideElementsInCurrentOnly>false</hideElementsInCurrentOnly>
<bounds x="38" y="757" width="220" height="87"/>
</OView>
<OView class="oracle.dbtools.crest.swingui.logical.TVEntity" oid="C798FBFB-01E3-3E20-A363-6121C82773D4" otype="Entity" vid="567BD3AA-2A43-854F-9831-40E9362C2522">
<hideElementsInCurrentOnly>false</hideElementsInCurrentOnly>
<bounds x="1006" y="713" width="217" height="144"/>
</OView>
<OView class="oracle.dbtools.crest.swingui.logical.TVEntity" oid="D16BAFBC-077F-6EF9-DDF9-DFABA1024964" otype="Entity" vid="7928B582-26B8-8729-F784-07C97C434591">
<hideElementsInCurrentOnly>false</hideElementsInCurrentOnly>
<bounds x="1022" y="326" width="238" height="130"/>
</OView>
<OView class="oracle.dbtools.crest.swingui.logical.TVEntity" oid="D71EBD75-B6D1-3B1A-D1EE-48CEA8A9CE50" otype="Entity" vid="34A1F724-DF1B-4A83-4433-B94844787D94">
<hideElementsInCurrentOnly>false</hideElementsInCurrentOnly>
<bounds x="301" y="187" width="288" height="438"/>
</OView>
</objectViews>
<connectors>
<Connector class="oracle.dbtools.crest.swingui.logical.TVRelation" oid="03A4DC40-D12E-CD89-AB8C-0A1B9BF4290C" otype="Relation" vid_source="CA4BF46B-0E19-F79D-E360-842680E6AA9E" vid_target="34A1F724-DF1B-4A83-4433-B94844787D94">
<hideElementsInCurrentOnly>false</hideElementsInCurrentOnly>
<lineWidth>1</lineWidth>
<points>
<point x="669" y="701"/>
<point x="566" y="701"/>
<point x="566" y="625"/>
</points>
</Connector>
<Connector class="oracle.dbtools.crest.swingui.logical.TVRelation" oid="06DC1E62-2A06-D524-0E01-7D1CA28CDA81" otype="Relation" vid_source="567BD3AA-2A43-854F-9831-40E9362C2522" vid_target="9F644485-0BE1-F76D-036E-B1B4823BE5FE">
<hideElementsInCurrentOnly>false</hideElementsInCurrentOnly>
<lineWidth>1</lineWidth>
<points>
<point x="1056" y="713"/>
<point x="1056" y="667"/>
<point x="1056" y="633"/>
</points>
</Connector>
<Connector class="oracle.dbtools.crest.swingui.logical.TVRelation" oid="0A34A6C0-7C0B-2712-8D94-C8DBA384DEC7" otype="Relation" vid_source="34A1F724-DF1B-4A83-4433-B94844787D94" vid_target="9F644485-0BE1-F76D-036E-B1B4823BE5FE">
<hideElementsInCurrentOnly>false</hideElementsInCurrentOnly>
<lineWidth>1</lineWidth>
<points>
<point x="589" y="483"/>
<point x="638" y="483"/>
<point x="636" y="589"/>
<point x="982" y="589"/>
</points>
</Connector>
<Connector class="oracle.dbtools.crest.swingui.logical.TVRelation" oid="1B6992DE-1410-E9DE-1D15-4F88F1CDB80D" otype="Relation" vid_source="D381CD95-20E2-6915-C7D4-B9BF6B244552" vid_target="34A1F724-DF1B-4A83-4433-B94844787D94">
<hideElementsInCurrentOnly>false</hideElementsInCurrentOnly>
<lineWidth>1</lineWidth>
<points>
<point x="260" y="490"/>
<point x="301" y="490"/>
</points>
</Connector>
<Connector class="oracle.dbtools.crest.swingui.logical.TVRelation" oid="2AEFB3EA-BB58-5A3B-5087-8E227B66937F" otype="Relation" vid_source="34A1F724-DF1B-4A83-4433-B94844787D94" vid_target="CC596B5D-87EF-9AD9-D44F-B559A1619A39">
<hideElementsInCurrentOnly>false</hideElementsInCurrentOnly>
<lineWidth>1</lineWidth>
<points>
<point x="301" y="603"/>
<point x="226" y="603"/>
<point x="226" y="757"/>
</points>
</Connector>
<Connector class="oracle.dbtools.crest.swingui.logical.TVRelation" oid="36D34B6F-AD4F-F158-5D7E-9EC1F5085C89" otype="Relation" vid_source="34A1F724-DF1B-4A83-4433-B94844787D94" vid_target="95CCEA23-4139-0E69-4CB4-310AC9990181">
<hideElementsInCurrentOnly>false</hideElementsInCurrentOnly>
<lineWidth>1</lineWidth>
<points>
<point x="301" y="229"/>
<point x="195" y="229"/>
</points>
</Connector>
<Connector class="oracle.dbtools.crest.swingui.logical.TVRelation" oid="45D2FA88-98FF-F1F4-524E-BA04305BE78E" otype="Relation" vid_source="567BD3AA-2A43-854F-9831-40E9362C2522" vid_target="7928B582-26B8-8729-F784-07C97C434591">
<hideElementsInCurrentOnly>false</hideElementsInCurrentOnly>
<lineWidth>1</lineWidth>
<points>
<point x="1223" y="778"/>
<point x="1251" y="778"/>
<point x="1251" y="456"/>
</points>
</Connector>
<Connector class="oracle.dbtools.crest.swingui.logical.TVRelation" oid="533676F2-69EE-4492-0A77-705EB9FA1097" otype="Relation" vid_source="34A1F724-DF1B-4A83-4433-B94844787D94" vid_target="D836CA6E-3B79-7F6E-B62D-11BB7491EAA0">
<hideElementsInCurrentOnly>false</hideElementsInCurrentOnly>
<lineWidth>1</lineWidth>
<points>
<point x="321" y="187"/>
<point x="321" y="113"/>
</points>
</Connector>
<Connector class="oracle.dbtools.crest.swingui.logical.TVRelation" oid="557A8F6E-1B62-C437-DE1C-23C7274C3137" otype="Relation" vid_source="34A1F724-DF1B-4A83-4433-B94844787D94" vid_target="7928B582-26B8-8729-F784-07C97C434591">
<hideElementsInCurrentOnly>false</hideElementsInCurrentOnly>
<lineWidth>1</lineWidth>
<points>
<point x="568" y="187"/>
<point x="568" y="153"/>
<point x="1198" y="155"/>
<point x="1198" y="326"/>
</points>
</Connector>
<Connector class="oracle.dbtools.crest.swingui.logical.TVRelation" oid="5AFC0032-FC61-BCA6-DA10-3D3794A05E7B" otype="Relation" vid_source="34A1F724-DF1B-4A83-4433-B94844787D94" vid_target="4F6CDB0B-B8B5-CA93-726A-9C340BDFDA1A">
<hideElementsInCurrentOnly>false</hideElementsInCurrentOnly>
<lineWidth>1</lineWidth>
<points>
<point x="589" y="420"/>
<point x="638" y="420"/>
<point x="664" y="420"/>
</points>
</Connector>
<Connector class="oracle.dbtools.crest.swingui.logical.TVRelation" oid="5C7252D2-FBA6-6E08-05A0-5AB9EDC74677" otype="Relation" vid_source="34A1F724-DF1B-4A83-4433-B94844787D94" vid_target="668839F0-B981-A9AF-F122-644E4D57CA26">
<hideElementsInCurrentOnly>false</hideElementsInCurrentOnly>
<lineWidth>1</lineWidth>
<points>
<point x="589" y="246"/>
<point x="675" y="246"/>
</points>
</Connector>
<Connector class="oracle.dbtools.crest.swingui.logical.TVRelation" oid="679A2C55-5B55-A1D5-7DE2-7DF804CC8894" otype="Relation" vid_source="304506D0-FFBA-2498-3AD4-5DDDB6F5CD72" vid_target="34A1F724-DF1B-4A83-4433-B94844787D94">
<hideElementsInCurrentOnly>false</hideElementsInCurrentOnly>
<lineWidth>1</lineWidth>
<points>
<point x="400" y="694"/>
<point x="400" y="625"/>
</points>
</Connector>
<Connector class="oracle.dbtools.crest.swingui.logical.TVRelation" oid="7C050971-3DEB-3AFA-84FD-4698848FF3F4" otype="Relation" vid_source="CC596B5D-87EF-9AD9-D44F-B559A1619A39" vid_target="CA4BF46B-0E19-F79D-E360-842680E6AA9E">
<hideElementsInCurrentOnly>false</hideElementsInCurrentOnly>
<lineWidth>1</lineWidth>
<points>
<point x="227" y="844"/>
<point x="227" y="886"/>
<point x="669" y="886"/>
</points>
</Connector>
<Connector class="oracle.dbtools.crest.swingui.logical.TVRelation" oid="856F1B74-F838-09B4-DF0E-F3EA46721109" otype="Relation" vid_source="CA4BF46B-0E19-F79D-E360-842680E6AA9E" vid_target="34A1F724-DF1B-4A83-4433-B94844787D94">
<hideElementsInCurrentOnly>false</hideElementsInCurrentOnly>
<lineWidth>1</lineWidth>
<points>
<point x="669" y="718"/>
<point x="541" y="718"/>
<point x="541" y="625"/>
</points>
</Connector>
<Connector class="oracle.dbtools.crest.swingui.logical.TVRelation" oid="9053BDFC-850C-4713-DD25-87D5410EFB0F" otype="Relation" vid_source="CA4BF46B-0E19-F79D-E360-842680E6AA9E" vid_target="9F644485-0BE1-F76D-036E-B1B4823BE5FE">
<hideElementsInCurrentOnly>false</hideElementsInCurrentOnly>
<lineWidth>1</lineWidth>
<points>
<point x="886" y="681"/>
<point x="1015" y="681"/>
<point x="1015" y="633"/>
</points>
</Connector>
<Connector class="oracle.dbtools.crest.swingui.logical.TVRelation" oid="B1F961DC-A3F3-D51C-D721-096751D92867" otype="Relation" vid_source="9F644485-0BE1-F76D-036E-B1B4823BE5FE" vid_target="7928B582-26B8-8729-F784-07C97C434591">
<hideElementsInCurrentOnly>false</hideElementsInCurrentOnly>
<lineWidth>1</lineWidth>
<points>
<point x="1162" y="519"/>
<point x="1162" y="461"/>
<point x="1162" y="456"/>
</points>
</Connector>
<Connector class="oracle.dbtools.crest.swingui.logical.TVRelation" oid="B26D1FDC-FD57-CAF3-AFAC-BB2A8A834649" otype="Relation" vid_source="304506D0-FFBA-2498-3AD4-5DDDB6F5CD72" vid_target="CA4BF46B-0E19-F79D-E360-842680E6AA9E">
<hideElementsInCurrentOnly>false</hideElementsInCurrentOnly>
<lineWidth>1</lineWidth>
<points>
<point x="498" y="735"/>
<point x="624" y="735"/>
<point x="669" y="735"/>
</points>
</Connector>
<Connector class="oracle.dbtools.crest.swingui.logical.TVRelation" oid="B889B903-F7D7-D6E5-6D37-2CCDDF91A28B" otype="Relation" vid_source="567BD3AA-2A43-854F-9831-40E9362C2522" vid_target="34A1F724-DF1B-4A83-4433-B94844787D94">
<hideElementsInCurrentOnly>false</hideElementsInCurrentOnly>
<lineWidth>1</lineWidth>
<points>
<point x="1006" y="772"/>
<point x="916" y="772"/>
<point x="911" y="614"/>
<point x="626" y="614"/>
<point x="626" y="514"/>
<point x="589" y="514"/>
</points>
</Connector>
<Connector class="oracle.dbtools.crest.swingui.logical.TVRelation" oid="BCF85238-6856-83E8-BA25-33195001D9AC" otype="Relation" vid_source="668839F0-B981-A9AF-F122-644E4D57CA26" vid_target="4F6CDB0B-B8B5-CA93-726A-9C340BDFDA1A">
<hideElementsInCurrentOnly>false</hideElementsInCurrentOnly>
<lineWidth>1</lineWidth>
<points>
<point x="734" y="306"/>
<point x="734" y="339"/>
<point x="734" y="398"/>
</points>
</Connector>
<Connector class="oracle.dbtools.crest.swingui.logical.TVRelation" oid="D22803EF-5DE8-7A3A-380D-3D1059E9D9CF" otype="Relation" vid_source="34A1F724-DF1B-4A83-4433-B94844787D94" vid_target="7A1BDCD1-4C87-C46F-AA9D-636A775755B6">
<hideElementsInCurrentOnly>false</hideElementsInCurrentOnly>
<lineWidth>1</lineWidth>
<points>
<point x="301" y="350"/>
<point x="231" y="350"/>
</points>
</Connector>
<Connector class="oracle.dbtools.crest.swingui.logical.TVRelation" oid="ECD4DCCA-636F-069F-2E2A-36F6AD6FF00F" otype="Relation" vid_source="567BD3AA-2A43-854F-9831-40E9362C2522" vid_target="668839F0-B981-A9AF-F122-644E4D57CA26">
<hideElementsInCurrentOnly>false</hideElementsInCurrentOnly>
<lineWidth>1</lineWidth>
<points>
<point x="1006" y="739"/>
<point x="949" y="739"/>
<point x="942" y="296"/>
<point x="895" y="296"/>
</points>
</Connector>
<Connector class="oracle.dbtools.crest.swingui.logical.TVRelation" oid="EE8A7541-7A94-9D05-D858-AD09C744522D" otype="Relation" vid_source="D836CA6E-3B79-7F6E-B62D-11BB7491EAA0" vid_target="863BF41D-2138-0B14-92F0-C62DCE38712C">
<hideElementsInCurrentOnly>false</hideElementsInCurrentOnly>
<lineWidth>1</lineWidth>
<points>
<point x="341" y="58"/>
<point x="458" y="58"/>
</points>
</Connector>
<Connector class="oracle.dbtools.crest.swingui.logical.TVRelation" oid="F21CA2F4-8C89-539E-FAB1-7CA0550FBE23" otype="Relation" vid_source="668839F0-B981-A9AF-F122-644E4D57CA26" vid_target="F7E93877-3995-E044-1E2A-DD487B960023">
<hideElementsInCurrentOnly>false</hideElementsInCurrentOnly>
<lineWidth>1</lineWidth>
<points>
<point x="895" y="232"/>
<point x="954" y="232"/>
</points>
</Connector>
</connectors>
</Diagram>